channel_advisor_api/__init__.py
channel_advisor_api/models/__init__.py
channel_advisor_api/models/channel_advisor.py
channel_advisor_api/models/channel_advisor_attributes.py
channel_advisor_api/models/channel_advisor_cleanup.py
channel_advisor_api/models/channel_advisor_client.py
channel_advisor_api/models/channel_advisor_dc.py
channel_advisor_api/models/channel_advisor_export.py
channel_advisor_api/models/channel_advisor_llm.py
channel_advisor_api/models/restricted_words.py
channel_advisor_api/utils/aws.py
channel_advisor_api/utils/logger.py
channel_advisor_api_python-0.2.3.dist-info/METADATA
channel_advisor_api_python-0.2.3.dist-info/WHEEL
channel_advisor_api_python-0.2.3.dist-info/RECORD
